amcp/__init__.py
amcp/__main__.py
amcp/_version.py
amcp/acp_agent.py
amcp/agent.py
amcp/agent_spec.py
amcp/apply_patch.py
amcp/chat.py
amcp/cli.py
amcp/commands.py
amcp/compaction.py
amcp/config.py
amcp/event_bus.py
amcp/hooks.py
amcp/init_wizard.py
amcp/llm.py
amcp/mcp_client.py
amcp/message_queue.py
amcp/models_db.py
amcp/multi_agent.py
amcp/project_rules.py
amcp/readfile.py
amcp/skills.py
amcp/task.py
amcp/toad.py
amcp/tools.py
amcp/ui.py
amcp/client/__init__.py
amcp/client/base.py
amcp/client/embedded.py
amcp/client/exceptions.py
amcp/client/http_client.py
amcp/client/session.py
amcp/client/ws_client.py
amcp/prompts/__init__.py
amcp/prompts/manager.py
amcp/prompts/templates/coder.md
amcp/prompts/templates/coder_anthropic.md
amcp/prompts/templates/compact.md
amcp/prompts/templates/explorer.md
amcp/prompts/templates/initialize.md
amcp/prompts/templates/planner.md
amcp/protocol/__init__.py
amcp/protocol/adapter.py
amcp/protocol/converters.py
amcp/protocol/error_codes.py
amcp/server/__init__.py
amcp/server/app.py
amcp/server/config.py
amcp/server/event_bridge.py
amcp/server/events.py
amcp/server/models.py
amcp/server/session_manager.py
amcp/server/websocket.py
amcp/server/routes/__init__.py
amcp/server/routes/agents.py
amcp/server/routes/health.py
amcp/server/routes/sessions.py
amcp/server/routes/tools.py
amcp_agent-0.9.0.dist-info/METADATA
amcp_agent-0.9.0.dist-info/WHEEL
amcp_agent-0.9.0.dist-info/entry_points.txt
amcp_agent-0.9.0.dist-info/RECORD
