Metadata-Version: 2.4
Name: amcp-agent
Version: 0.9.0
Summary: amcp: Lego-style coding agent CLI. Core: rg grep/find and read; editing & web search via MCP.
Project-URL: Homepage, https://github.com/tao12345666333/amcp
Project-URL: Repository, https://github.com/tao12345666333/amcp
Project-URL: Issues, https://github.com/tao12345666333/amcp/issues
Author: tao
License: MIT
Keywords: agent,ai,cli,coding,llm,mcp
Classifier: Development Status :: 4 - Beta
Classifier: Environment :: Console
Classifier: Intended Audience :: Developers
Classifier: License :: OSI Approved :: MIT License
Classifier: Operating System :: OS Independent
Classifier: Programming Language :: Python :: 3
Classifier: Programming Language :: Python :: 3.11
Classifier: Programming Language :: Python :: 3.12
Classifier: Topic :: Software Development
Requires-Python: >=3.11
Requires-Dist: agent-client-protocol>=0.7.0
Requires-Dist: fastapi>=0.115.0
Requires-Dist: fastmcp<3,>=2.0.0
Requires-Dist: httpx>=0.27.0
Requires-Dist: openai>=1.52.0
Requires-Dist: prompt-toolkit>=3.0.0
Requires-Dist: pydantic>=2.7
Requires-Dist: pyyaml>=6.0
Requires-Dist: rich>=13.7.0
Requires-Dist: sse-starlette>=2.1.0
Requires-Dist: tomli-w>=1.0.0
Requires-Dist: tomli>=2.0.0; python_version < '3.11'
Requires-Dist: typer>=0.12.3
Requires-Dist: uvicorn>=0.30.0
Provides-Extra: anthropic
Requires-Dist: anthropic>=0.40.0; extra == 'anthropic'
Provides-Extra: dev
Requires-Dist: anthropic>=0.40.0; extra == 'dev'
Requires-Dist: mypy>=1.8.0; extra == 'dev'
Requires-Dist: pytest-asyncio>=0.23.0; extra == 'dev'
Requires-Dist: pytest-cov>=4.1.0; extra == 'dev'
Requires-Dist: pytest>=8.0.0; extra == 'dev'
Requires-Dist: ruff>=0.3.0; extra == 'dev'
Requires-Dist: types-pyyaml>=6.0.0; extra == 'dev'
Provides-Extra: tui
Requires-Dist: batrachian-toad>=0.5.18; (python_version >= '3.14') and extra == 'tui'
